nysiis/__init__.py
nysiis/nysiis.py
nysiis/six.py
nysiis/version.py
pynysiis-1.0.7.dist-info/LICENSE
pynysiis-1.0.7.dist-info/METADATA
pynysiis-1.0.7.dist-info/WHEEL
pynysiis-1.0.7.dist-info/top_level.txt
pynysiis-1.0.7.dist-info/RECORD
