Metadata-Version: 2.1
Name: pynysiis
Version: 1.0.7
Summary: NYSIIS phonetic encoding algorithm.
Home-page: https://finbarrs.eu/
Author: Finbarrs Oketunji
Author-email: f@finbarrs.eu
License: MIT
Project-URL: Bug Tracker, https://github.com/0xnu/nysiis/issues
Project-URL: Changes, https://github.com/0xnu/nysiis/blob/main/CHANGELOG.md
Project-URL: Documentation, https://github.com/0xnu/nysiis/blob/main/README.md
Project-URL: Source Code, https://github.com/0xnu/nysiis
Keywords: nysiis,phonetic,encoding,algorithm,name matching,fuzzy matching,sound matching
Classifier: Development Status :: 5 - Production/Stable
Classifier: Intended Audience :: Developers
Classifier: License :: OSI Approved :: MIT License
Classifier: Operating System :: OS Independent
Classifier: Programming Language :: Python :: 3 :: Only
Classifier: Programming Language :: Python :: 3.8
Classifier: Programming Language :: Python :: 3.9
Classifier: Programming Language :: Python :: 3.10
Classifier: Programming Language :: Python :: 3.11
Classifier: Programming Language :: Python :: 3.12
Classifier: Programming Language :: Python :: Implementation :: CPython
Classifier: Programming Language :: Python :: Implementation :: PyPy
Classifier: Topic :: Software Development :: Libraries :: Python Modules
Classifier: Topic :: Text Processing :: Linguistic
Requires-Python: >=3.8
License-File: LICENSE
Requires-Dist: pydantic
